odoo/addons/product_supplierinfo_for_customer/README.rst
odoo/addons/product_supplierinfo_for_customer/__init__.py
odoo/addons/product_supplierinfo_for_customer/__manifest__.py
odoo/addons/product_supplierinfo_for_customer/demo/product_demo.xml
odoo/addons/product_supplierinfo_for_customer/i18n/ca.po
odoo/addons/product_supplierinfo_for_customer/i18n/de.po
odoo/addons/product_supplierinfo_for_customer/i18n/es.po
odoo/addons/product_supplierinfo_for_customer/i18n/fr.po
odoo/addons/product_supplierinfo_for_customer/i18n/it.po
odoo/addons/product_supplierinfo_for_customer/i18n/product_supplierinfo_for_customer.pot
odoo/addons/product_supplierinfo_for_customer/i18n/sl.po
odoo/addons/product_supplierinfo_for_customer/models/__init__.py
odoo/addons/product_supplierinfo_for_customer/models/product_customerinfo.py
odoo/addons/product_supplierinfo_for_customer/models/product_pricelist.py
odoo/addons/product_supplierinfo_for_customer/models/product_product.py
odoo/addons/product_supplierinfo_for_customer/models/product_supplierinfo.py
odoo/addons/product_supplierinfo_for_customer/models/product_template.py
odoo/addons/product_supplierinfo_for_customer/models/res_partner.py
odoo/addons/product_supplierinfo_for_customer/readme/CONFIGURE.rst
odoo/addons/product_supplierinfo_for_customer/readme/CONTRIBUTORS.rst
odoo/addons/product_supplierinfo_for_customer/readme/DESCRIPTION.rst
odoo/addons/product_supplierinfo_for_customer/readme/ROADMAP.rst
odoo/addons/product_supplierinfo_for_customer/readme/USAGE.rst
odoo/addons/product_supplierinfo_for_customer/security/ir.model.access.csv
odoo/addons/product_supplierinfo_for_customer/static/description/icon.png
odoo/addons/product_supplierinfo_for_customer/static/description/index.html
odoo/addons/product_supplierinfo_for_customer/static/xls/product_customerinfo.xls
odoo/addons/product_supplierinfo_for_customer/tests/__init__.py
odoo/addons/product_supplierinfo_for_customer/tests/test_product_supplierinfo_for_customer.py
odoo14_addon_product_supplierinfo_for_customer-14.0.2.0.3.dist-info/METADATA
odoo14_addon_product_supplierinfo_for_customer-14.0.2.0.3.dist-info/WHEEL
odoo14_addon_product_supplierinfo_for_customer-14.0.2.0.3.dist-info/top_level.txt
odoo14_addon_product_supplierinfo_for_customer-14.0.2.0.3.dist-info/RECORD
