Metadata-Version: 2.1
Name: odoo14-addon-product-supplierinfo-for-customer
Version: 14.0.2.0.3
Summary: Allows to define prices for customers in the products
Home-page: https://github.com/OCA/product-attribute
Author: AvanzOSC, Tecnativa, Odoo Community Association (OCA)
Author-email: support@odoo-community.org
License: AGPL-3
Platform: UNKNOWN
Classifier: Programming Language :: Python
Classifier: Framework :: Odoo
Classifier: Framework :: Odoo :: 14.0
Classifier: License :: OSI Approved :: GNU Affero General Public License v3
Classifier: Development Status :: 5 - Production/Stable
Requires-Python: >=3.6
Requires-Dist: odoo <14.1dev,>=14.0a
